<?xml version="1.0" encoding="utf-8"?>
<openerp>
    <data>
        <template id="report_employeereport">
            <t t-call="report.html_container">
                <t t-foreach="docs" t-as="o">
                    <t t-call="report.external_layout">
                        <div class="page">
                            <h2>Employee Report: </h2>
                            <p>We are family</p>
                        </div>
                    </t>
                </t>
            </t>
        </template>
    </data>
</openerp>
